[
  {
    "name": "Champions League - Play Offs",
    "country": "EUROPE",
    "flag_icon_local": "images/competitions/usl_championship_flag.png",
    "matches": [
      {
        "time": "19:00",
        "odds": [
          "2.38",
          "3.30",
          "3.00"
        ],
        "home_team": "PSG",
        "home_team_logo_local": "images/teams/psg_logo.png",
        "home_id": "team_20250628_032755864_psg_42ab3708",
        "away_team": "Arsenal",
        "away_team_logo_local": "images/teams/arsenal_logo.png",
        "away_id": "team_20250808_011234637_arsenal_c3995334",
        "id": "match_20260530_000348202_psg_arsenal_1900_625b1e",
        "status": "PREVIEW",
        "predictions": {
          "algorithm_version": "FINAL_BIVARIATE_POISSON_v2.0",
          "simulation_count": 100000,
          "top_3_correct_scores": [
            {
              "score": "1-1",
              "percentage": 12.04
            },
            {
              "score": "1-0",
              "percentage": 11.68
            },
            {
              "score": "2-1",
              "percentage": 8.48
            }
          ],
          "most_likely_halftime_score": {
            "score": "1-0",
            "percentage": 18.48
          },
          "goals_markets": {
            "over_1_5": 68.02,
            "over_2_5": 44.83,
            "under_2_5": 55.17,
            "under_3_5": 73.86
          },
          "teams_markets": {
            "both_teams_score": 50.43
          },
          "market_analysis": {
            "home_win_prob": 0.39768618944323936,
            "draw_prob": 0.28681610026512416,
            "away_win_prob": 0.31549771029163654,
            "market_efficiency": 0.9464931308749097,
            "goal_expectancy": 0.02400000000000002,
            "overround": 0.05653170359052706,
            "odds_strength_ratio": 1.2605042016806722
          },
          "team_values": {
            "home_team_value": 80,
            "away_team_value": 75.0
          }
        }
      }
    ],
    "total_matches": 1
  },
  {
    "name": "Primera Nacional",
    "country": "ARGENTINA",
    "flag_icon_local": "images/competitions/primera_nacional_flag.png",
    "matches": [
      {
        "time": "03:00",
        "odds": [
          "3.00",
          "2.70",
          "2.70"
        ],
        "home_team": "Racing Cordoba",
        "home_team_logo_local": "images/teams/racing_cordoba_logo.png",
        "home_id": "team_20250628_032836453_racingcordoba_bee637d8",
        "away_team": "Ferro",
        "away_team_logo_local": "images/teams/ferro_logo.png",
        "away_id": "team_20250705_000251113_ferro_faf30e76",
        "id": "match_20260530_000448750_racingcordoba_ferro_0300_ad285e",
        "status": "scheduled",
        "predictions": {
          "algorithm_version": "FINAL_BIVARIATE_POISSON_v2.0",
          "simulation_count": 100000,
          "top_3_correct_scores": [
            {
              "score": "1-2",
              "percentage": 9.63
            },
            {
              "score": "1-1",
              "percentage": 8.84
            },
            {
              "score": "2-1",
              "percentage": 7.24
            }
          ],
          "most_likely_halftime_score": {
            "score": "1-1",
            "percentage": 14.69
          },
          "goals_markets": {
            "over_1_5": 78.2,
            "over_2_5": 57.9,
            "under_2_5": 42.1,
            "under_3_5": 61.69
          },
          "teams_markets": {
            "both_teams_score": 61.18
          },
          "market_analysis": {
            "home_win_prob": 0.3103448275862069,
            "draw_prob": 0.3448275862068966,
            "away_win_prob": 0.3448275862068966,
            "market_efficiency": 0.9310344827586208,
            "goal_expectancy": 0.09599999999999997,
            "overround": 0.07407407407407396,
            "odds_strength_ratio": 0.9
          },
          "team_values": {
            "home_team_value": 56.3,
            "away_team_value": 62.7
          }
        }
      },
      {
        "time": "21:00",
        "odds": [
          "2.55",
          "2.57",
          "3.30"
        ],
        "home_team": "CA Estudiantes",
        "home_team_logo_local": "images/teams/ca_estudiantes_logo.png",
        "home_id": "team_20250628_032826363_caestudiantes_ce8529d0",
        "away_team": "Godoy Cruz",
        "away_team_logo_local": "images/teams/godoy_cruz_logo.png",
        "away_id": "team_20250711_000258949_godoycruz_41315693",
        "id": "match_20260530_000458865_caestudiantes_godoycruz_2100_3faed4",
        "status": "scheduled",
        "predictions": {
          "algorithm_version": "FINAL_BIVARIATE_POISSON_v2.0",
          "simulation_count": 100000,
          "top_3_correct_scores": [
            {
              "score": "0-0",
              "percentage": 16.73
            },
            {
              "score": "1-0",
              "percentage": 12.44
            },
            {
              "score": "0-1",
              "percentage": 11.78
            }
          ],
          "most_likely_halftime_score": {
            "score": "0-0",
            "percentage": 22.83
          },
          "goals_markets": {
            "over_1_5": 59.35,
            "over_2_5": 35.51,
            "under_2_5": 64.49,
            "under_3_5": 81.46
          },
          "teams_markets": {
            "both_teams_score": 43.38
          },
          "market_analysis": {
            "home_win_prob": 0.36167082453783667,
            "draw_prob": 0.3588562655920169,
            "away_win_prob": 0.2794729098701465,
            "market_efficiency": 0.9222606025714833,
            "goal_expectancy": 0.11160000000000002,
            "overround": 0.08429222414115989,
            "odds_strength_ratio": 1.2941176470588236
          },
          "team_values": {
            "home_team_value": 50.7,
            "away_team_value": 53.9
          }
        }
      },
      {
        "time": "21:00",
        "odds": [
          "1.79",
          "3.10",
          "5.00"
        ],
        "home_team": "Colegiales",
        "home_team_logo_local": "images/teams/colegiales_logo.png",
        "home_id": "team_20250704_003806901_colegiales_a38059df",
        "away_team": "Agropecuario",
        "away_team_logo_local": "images/teams/agropecuario_logo.png",
        "away_id": "team_20250628_032906791_agropecuario_fb774b95",
        "id": "match_20260530_000509370_colegiales_agropecuario_2100_e9f7ba",
        "status": "scheduled",
        "predictions": {
          "algorithm_version": "FINAL_BIVARIATE_POISSON_v2.0",
          "simulation_count": 100000,
          "top_3_correct_scores": [
            {
              "score": "1-0",
              "percentage": 12.28
            },
            {
              "score": "1-1",
              "percentage": 11.4
            },
            {
              "score": "2-1",
              "percentage": 8.88
            }
          ],
          "most_likely_halftime_score": {
            "score": "1-0",
            "percentage": 17.94
          },
          "goals_markets": {
            "over_1_5": 71.56,
            "over_2_5": 49.27,
            "under_2_5": 50.73,
            "under_3_5": 69.98
          },
          "teams_markets": {
            "both_teams_score": 52.09
          },
          "market_analysis": {
            "home_win_prob": 0.516683889462982,
            "draw_prob": 0.2983432781092703,
            "away_win_prob": 0.18497283242774762,
            "market_efficiency": 0.924864162138738,
            "goal_expectancy": 0.04799999999999999,
            "overround": 0.08123986303838526,
            "odds_strength_ratio": 2.793296089385475
          },
          "team_values": {
            "home_team_value": 56.4,
            "away_team_value": 52.4
          }
        }
      },
      {
        "time": "21:30",
        "odds": [
          "2.20",
          "2.55",
          "4.20"
        ],
        "home_team": "All Boys",
        "home_team_logo_local": "images/teams/all_boys_logo.png",
        "home_id": "team_20250628_032816276_allboys_68988c2f",
        "away_team": "Los Andes",
        "away_team_logo_local": "images/teams/los_andes_logo.png",
        "away_id": "team_20250628_032846559_losandes_8bebc1c0",
        "id": "match_20260530_000519506_allboys_losandes_2130_2d07af",
        "status": "scheduled",
        "predictions": {
          "algorithm_version": "FINAL_BIVARIATE_POISSON_v2.0",
          "simulation_count": 100000,
          "top_3_correct_scores": [
            {
              "score": "1-0",
              "percentage": 13.15
            },
            {
              "score": "1-1",
              "percentage": 11.57
            },
            {
              "score": "0-1",
              "percentage": 11.21
            }
          ],
          "most_likely_halftime_score": {
            "score": "0-0",
            "percentage": 21.73
          },
          "goals_markets": {
            "over_1_5": 63.42,
            "over_2_5": 40.3,
            "under_2_5": 59.7,
            "under_3_5": 77.51
          },
          "teams_markets": {
            "both_teams_score": 47.34
          },
          "market_analysis": {
            "home_win_prob": 0.41901408450704225,
            "draw_prob": 0.36150234741784043,
            "away_win_prob": 0.21948356807511735,
            "market_efficiency": 0.921830985915493,
            "goal_expectancy": 0.11400000000000002,
            "overround": 0.0847975553857907,
            "odds_strength_ratio": 1.909090909090909
          },
          "team_values": {
            "home_team_value": 61.5,
            "away_team_value": 62.0
          }
        }
      },
      {
        "time": "21:30",
        "odds": [
          "2.75",
          "2.65",
          "3.00"
        ],
        "home_team": "Almirante Brown",
        "home_team_logo_local": "images/teams/almirante_brown_logo.png",
        "home_id": "team_20250706_000244719_almirantebrown_f5b700da",
        "away_team": "Colon Santa Fe",
        "away_team_logo_local": "images/teams/colon_santa_fe_logo.png",
        "away_id": "team_20250630_000233243_colonsantafe_d89bc3f7",
        "id": "match_20260530_000529660_almirantebrown_colonsantafe_2130_9d293b",
        "status": "scheduled",
        "predictions": {
          "algorithm_version": "FINAL_BIVARIATE_POISSON_v2.0",
          "simulation_count": 100000,
          "top_3_correct_scores": [
            {
              "score": "1-0",
              "percentage": 14.86
            },
            {
              "score": "0-0",
              "percentage": 13.61
            },
            {
              "score": "0-1",
              "percentage": 12.23
            }
          ],
          "most_likely_halftime_score": {
            "score": "0-0",
            "percentage": 24.09
          },
          "goals_markets": {
            "over_1_5": 61.17,
            "over_2_5": 38.2,
            "under_2_5": 61.8,
            "under_3_5": 78.87
          },
          "teams_markets": {
            "both_teams_score": 46.3
          },
          "market_analysis": {
            "home_win_prob": 0.33847791378392766,
            "draw_prob": 0.3512506652474721,
            "away_win_prob": 0.31027142096860033,
            "market_efficiency": 0.9308142629058009,
            "goal_expectancy": 0.10200000000000001,
            "overround": 0.07432818753573467,
            "odds_strength_ratio": 1.0909090909090908
          },
          "team_values": {
            "home_team_value": 57.4,
            "away_team_value": 52.7
          }
        }
      },
      {
        "time": "21:30",
        "odds": [
          "1.76",
          "3.20",
          "5.00"
        ],
        "home_team": "Def. de Belgrano",
        "home_team_logo_local": "images/teams/def._de_belgrano_logo.png",
        "home_id": "team_20250705_000321501_defdebelgrano_521fbac1",
        "away_team": "San Telmo",
        "away_team_logo_local": "images/teams/san_telmo_logo.png",
        "away_id": "team_20250704_003816214_santelmo_f36929bd",
        "id": "match_20260530_000539811_defdebelgrano_santelmo_2130_e4bfaf",
        "status": "scheduled",
        "predictions": {
          "algorithm_version": "FINAL_BIVARIATE_POISSON_v2.0",
          "simulation_count": 100000,
          "top_3_correct_scores": [
            {
              "score": "1-0",
              "percentage": 12.21
            },
            {
              "score": "2-1",
              "percentage": 9.6
            },
            {
              "score": "1-1",
              "percentage": 9.49
            }
          ],
          "most_likely_halftime_score": {
            "score": "1-0",
            "percentage": 17.7
          },
          "goals_markets": {
            "over_1_5": 73.22,
            "over_2_5": 51.79,
            "under_2_5": 48.21,
            "under_3_5": 67.17
          },
          "teams_markets": {
            "both_teams_score": 53.52
          },
          "market_analysis": {
            "home_win_prob": 0.5257623554153522,
            "draw_prob": 0.2891692954784437,
            "away_win_prob": 0.18506834910620398,
            "market_efficiency": 0.9253417455310199,
            "goal_expectancy": 0.035999999999999976,
            "overround": 0.0806818181818183,
            "odds_strength_ratio": 2.840909090909091
          },
          "team_values": {
            "home_team_value": 54.4,
            "away_team_value": 50.3
          }
        }
      }
    ],
    "total_matches": 6
  },
  {
    "name": "Primera B",
    "country": "ARGENTINA",
    "flag_icon_local": "images/competitions/primera_b_-_apertura_flag.png",
    "matches": [
      {
        "time": "20:30",
        "odds": [
          "2.02",
          "2.86",
          "3.93"
        ],
        "home_team": "Comunicaciones",
        "home_team_logo_local": "images/teams/comunicaciones_logo.png",
        "home_id": "team_20250628_033047956_comunicaciones_2da6c90f",
        "away_team": "Deportivo Armenio",
        "away_team_logo_local": "images/teams/deportivo_armenio_logo.png",
        "away_id": "team_20250704_004027867_deportivoarmenio_d447a2ef",
        "id": "match_20260530_000650437_comunicaciones_deportivoarmenio_2030_31efb9",
        "status": "scheduled",
        "predictions": {
          "algorithm_version": "FINAL_BIVARIATE_POISSON_v2.0",
          "simulation_count": 100000,
          "top_3_correct_scores": [
            {
              "score": "2-1",
              "percentage": 11.02
            },
            {
              "score": "1-0",
              "percentage": 10.57
            },
            {
              "score": "2-0",
              "percentage": 9.75
            }
          ],
          "most_likely_halftime_score": {
            "score": "1-0",
            "percentage": 14.96
          },
          "goals_markets": {
            "over_1_5": 74.03,
            "over_2_5": 53.02,
            "under_2_5": 46.98,
            "under_3_5": 66.33
          },
          "teams_markets": {
            "both_teams_score": 53.07
          },
          "market_analysis": {
            "home_win_prob": 0.450391896007309,
            "draw_prob": 0.3181089615156518,
            "away_win_prob": 0.23149914247703923,
            "market_efficiency": 0.9097916299347641,
            "goal_expectancy": 0.07680000000000001,
            "overround": 0.09915278080949608,
            "odds_strength_ratio": 1.9455445544554455
          },
          "team_values": {
            "home_team_value": 66.3,
            "away_team_value": 47.6
          }
        }
      },
      {
        "time": "20:30",
        "odds": [
          "2.48",
          "2.50",
          "3.38"
        ],
        "home_team": "Dock Sud",
        "home_team_logo_local": "images/teams/dock_sud_logo.png",
        "home_id": "team_20250628_033047944_docksud_f966d395",
        "away_team": "Brown Adrogue",
        "away_team_logo_local": "images/teams/brown_adrogue_logo.png",
        "away_id": "team_20250704_003957551_brownadrogue_c50526de",
        "id": "match_20260530_000700596_docksud_brownadrogue_2030_5686b4",
        "status": "scheduled",
        "predictions": {
          "algorithm_version": "FINAL_BIVARIATE_POISSON_v2.0",
          "simulation_count": 100000,
          "top_3_correct_scores": [
            {
              "score": "1-0",
              "percentage": 10.21
            },
            {
              "score": "2-1",
              "percentage": 10.05
            },
            {
              "score": "1-1",
              "percentage": 9.79
            }
          ],
          "most_likely_halftime_score": {
            "score": "1-0",
            "percentage": 17.38
          },
          "goals_markets": {
            "over_1_5": 71.84,
            "over_2_5": 49.72,
            "under_2_5": 50.28,
            "under_3_5": 69.47
          },
          "teams_markets": {
            "both_teams_score": 53.74
          },
          "market_analysis": {
            "home_win_prob": 0.3668744898490822,
            "draw_prob": 0.3639394939302895,
            "away_win_prob": 0.2691860162206284,
            "market_efficiency": 0.9098487348257238,
            "goal_expectancy": 0.12,
            "overround": 0.09908379461729333,
            "odds_strength_ratio": 1.3629032258064515
          },
          "team_values": {
            "home_team_value": 53.2,
            "away_team_value": 48.3
          }
        }
      },
      {
        "time": "21:30",
        "odds": [
          "1.84",
          "2.96",
          "4.60"
        ],
        "home_team": "Real Pilar",
        "home_team_logo_local": "images/teams/real_pilar_logo.png",
        "home_id": "team_20250628_033037816_realpilar_8e535496",
        "away_team": "UAI Urquiza",
        "away_team_logo_local": "images/teams/uai_urquiza_logo.png",
        "away_id": "team_20250628_033118223_uaiurquiza_aad2b989",
        "id": "match_20260530_000710749_realpilar_uaiurquiza_2130_9632ad",
        "status": "scheduled",
        "predictions": {
          "algorithm_version": "FINAL_BIVARIATE_POISSON_v2.0",
          "simulation_count": 100000,
          "top_3_correct_scores": [
            {
              "score": "2-0",
              "percentage": 11.47
            },
            {
              "score": "1-0",
              "percentage": 10.92
            },
            {
              "score": "2-1",
              "percentage": 9.75
            }
          ],
          "most_likely_halftime_score": {
            "score": "2-0",
            "percentage": 16.1
          },
          "goals_markets": {
            "over_1_5": 78.14,
            "over_2_5": 57.77,
            "under_2_5": 42.23,
            "under_3_5": 61.92
          },
          "teams_markets": {
            "both_teams_score": 51.7
          },
          "market_analysis": {
            "home_win_prob": 0.4946524064171123,
            "draw_prob": 0.3074866310160428,
            "away_win_prob": 0.19786096256684496,
            "market_efficiency": 0.9101604278074867,
            "goal_expectancy": 0.0648,
            "overround": 0.09870740305522907,
            "odds_strength_ratio": 2.4999999999999996
          },
          "team_values": {
            "home_team_value": 69.5,
            "away_team_value": 51.6
          }
        }
      }
    ],
    "total_matches": 3
  },
  {
    "name": "Primera C",
    "country": "ARGENTINA",
    "flag_icon_local": "images/competitions/primera_c_flag.png",
    "matches": [
      {
        "time": "18:30",
        "odds": [
          "3.00",
          "2.66",
          "2.55"
        ],
        "home_team": "Central Ballester",
        "home_team_logo_local": "images/teams/central_ballester_logo.png",
        "home_id": "team_20250629_000248736_centralballester_ed009147",
        "away_team": "Deportivo Espanol",
        "away_team_logo_local": "images/teams/deportivo_espanol_logo.png",
        "away_id": "team_20250706_000305245_deportivoespanol_c692ddc1",
        "id": "match_20260530_000751227_centralballester_deportivoespanol_1830_e3568d",
        "status": "scheduled",
        "predictions": {
          "algorithm_version": "FINAL_BIVARIATE_POISSON_v2.0",
          "simulation_count": 100000,
          "top_3_correct_scores": [
            {
              "score": "2-1",
              "percentage": 8.74
            },
            {
              "score": "1-2",
              "percentage": 8.63
            },
            {
              "score": "1-1",
              "percentage": 7.83
            }
          ],
          "most_likely_halftime_score": {
            "score": "1-1",
            "percentage": 13.89
          },
          "goals_markets": {
            "over_1_5": 80.09,
            "over_2_5": 61.03,
            "under_2_5": 38.97,
            "under_3_5": 58.47
          },
          "teams_markets": {
            "both_teams_score": 63.05
          },
          "market_analysis": {
            "home_win_prob": 0.3026368625351358,
            "draw_prob": 0.34131976977646894,
            "away_win_prob": 0.3560433676883951,
            "market_efficiency": 0.9079105876054074,
            "goal_expectancy": 0.10079999999999997,
            "overround": 0.1014300457024917,
            "odds_strength_ratio": 0.85
          },
          "team_values": {
            "home_team_value": 50.8,
            "away_team_value": 63.0
          }
        }
      },
      {
        "time": "20:30",
        "odds": [
          "2.79",
          "2.74",
          "2.57"
        ],
        "home_team": "Claypole",
        "home_team_logo_local": "images/teams/claypole_logo.png",
        "home_id": "team_20250628_033138453_claypole_0bc921a4",
        "away_team": "Central Cordoba",
        "away_team_logo_local": "images/teams/central_cordoba_logo.png",
        "away_id": "team_20250629_000308589_centralcordoba_88032df3",
        "id": "match_20260530_000801318_claypole_centralcordoba_2030_2789c5",
        "status": "scheduled",
        "predictions": {
          "algorithm_version": "FINAL_BIVARIATE_POISSON_v2.0",
          "simulation_count": 100000,
          "top_3_correct_scores": [
            {
              "score": "1-0",
              "percentage": 17.6
            },
            {
              "score": "2-0",
              "percentage": 12.25
            },
            {
              "score": "0-0",
              "percentage": 10.58
            }
          ],
          "most_likely_halftime_score": {
            "score": "1-0",
            "percentage": 24.61
          },
          "goals_markets": {
            "over_1_5": 63.41,
            "over_2_5": 40.48,
            "under_2_5": 59.52,
            "under_3_5": 77.11
          },
          "teams_markets": {
            "both_teams_score": 41.53
          },
          "market_analysis": {
            "home_win_prob": 0.322180384046997,
            "draw_prob": 0.3280595881354459,
            "away_win_prob": 0.3497600278175571,
            "market_efficiency": 0.8988832714911217,
            "goal_expectancy": 0.09119999999999998,
            "overround": 0.11249150108349415,
            "odds_strength_ratio": 0.9211469534050178
          },
          "team_values": {
            "home_team_value": 65.4,
            "away_team_value": 43.7
          }
        }
      },
      {
        "time": "20:30",
        "odds": [
          "1.84",
          "2.93",
          "4.61"
        ],
        "home_team": "El Porvenir",
        "home_team_logo_local": "images/teams/el_porvenir_logo.png",
        "home_id": "team_20250705_000714674_elporvenir_7d2aab25",
        "away_team": "Deportivo Muniz",
        "away_team_logo_local": "images/teams/deportivo_muniz_logo.png",
        "away_id": "team_20250706_000255105_deportivomuniz_a0295136",
        "id": "match_20260530_000811452_elporvenir_deportivomuniz_2030_088d3e",
        "status": "scheduled",
        "predictions": {
          "algorithm_version": "FINAL_BIVARIATE_POISSON_v2.0",
          "simulation_count": 100000,
          "top_3_correct_scores": [
            {
              "score": "0-0",
              "percentage": 16.32
            },
            {
              "score": "1-0",
              "percentage": 16.0
            },
            {
              "score": "0-1",
              "percentage": 10.86
            }
          ],
          "most_likely_halftime_score": {
            "score": "0-0",
            "percentage": 24.12
          },
          "goals_markets": {
            "over_1_5": 60.24,
            "over_2_5": 35.99,
            "under_2_5": 64.01,
            "under_3_5": 81.32
          },
          "teams_markets": {
            "both_teams_score": 42.99
          },
          "market_analysis": {
            "home_win_prob": 0.4933110306819718,
            "draw_prob": 0.309792592646699,
            "away_win_prob": 0.19689637667132928,
            "market_efficiency": 0.9076922964548281,
            "goal_expectancy": 0.06839999999999997,
            "overround": 0.1016949288935225,
            "odds_strength_ratio": 2.505434782608696
          },
          "team_values": {
            "home_team_value": 58.3,
            "away_team_value": 65.2
          }
        }
      },
      {
        "time": "20:30",
        "odds": [
          "1.70",
          "3.24",
          "4.90"
        ],
        "home_team": "Lugano",
        "home_team_logo_local": "images/teams/lugano_logo.png",
        "home_id": "team_20250628_033138441_lugano_733da6d7",
        "away_team": "Deportivo Paraguayo",
        "away_team_logo_local": "images/teams/deportivo_paraguayo_logo.png",
        "away_id": "team_20260320_001931134_deportivoparaguayo_92560961",
        "id": "match_20260530_000821601_lugano_deportivoparaguayo_2030_38d732",
        "status": "scheduled",
        "predictions": {
          "algorithm_version": "FINAL_BIVARIATE_POISSON_v2.0",
          "simulation_count": 100000,
          "top_3_correct_scores": [
            {
              "score": "1-0",
              "percentage": 17.74
            },
            {
              "score": "0-0",
              "percentage": 11.94
            },
            {
              "score": "2-0",
              "percentage": 11.15
            }
          ],
          "most_likely_halftime_score": {
            "score": "1-0",
            "percentage": 24.16
          },
          "goals_markets": {
            "over_1_5": 61.88,
            "over_2_5": 38.05,
            "under_2_5": 61.95,
            "under_3_5": 79.54
          },
          "teams_markets": {
            "both_teams_score": 43.49
          },
          "market_analysis": {
            "home_win_prob": 0.5342935989769133,
            "draw_prob": 0.28033923403109645,
            "away_win_prob": 0.1853671669919903,
            "market_efficiency": 0.9082991182607526,
            "goal_expectancy": 0.031199999999999974,
            "overround": 0.10095890207935021,
            "odds_strength_ratio": 2.882352941176471
          },
          "team_values": {
            "home_team_value": 73.6,
            "away_team_value": 57.4
          }
        }
      },
      {
        "time": "21:30",
        "odds": [
          "2.47",
          "2.81",
          "2.94"
        ],
        "home_team": "Argentino de Rosario",
        "home_team_logo_local": "images/teams/argentino_de_rosario_logo.png",
        "home_id": "team_20250629_000248154_argentinoderosario_1b1efde0",
        "away_team": "Estrella Del Sur",
        "away_team_logo_local": "images/teams/estrella_del_sur_logo.png",
        "away_id": "team_20250802_213617241_estrelladelsur_e1fc63e0",
        "id": "match_20260530_000831703_argentinoderosario_estrelladelsur_2130_03cf17",
        "status": "scheduled",
        "predictions": {
          "algorithm_version": "FINAL_BIVARIATE_POISSON_v2.0",
          "simulation_count": 100000,
          "top_3_correct_scores": [
            {
              "score": "0-1",
              "percentage": 15.89
            },
            {
              "score": "0-0",
              "percentage": 14.68
            },
            {
              "score": "1-0",
              "percentage": 10.81
            }
          ],
          "most_likely_halftime_score": {
            "score": "0-0",
            "percentage": 22.13
          },
          "goals_markets": {
            "over_1_5": 60.48,
            "over_2_5": 36.91,
            "under_2_5": 63.09,
            "under_3_5": 80.34
          },
          "teams_markets": {
            "both_teams_score": 44.89
          },
          "market_analysis": {
            "home_win_prob": 0.36776338926010177,
            "draw_prob": 0.3232653279261393,
            "away_win_prob": 0.30897128281375896,
            "market_efficiency": 0.9083755714724514,
            "goal_expectancy": 0.08279999999999998,
            "overround": 0.10086624013790679,
            "odds_strength_ratio": 1.1902834008097165
          },
          "team_values": {
            "home_team_value": 65.0,
            "away_team_value": 74.6
          }
        }
      },
      {
        "time": "21:30",
        "odds": [
          "2.45",
          "2.75",
          "3.03"
        ],
        "home_team": "Club Lujan",
        "home_team_logo_local": "images/teams/club_lujan_logo.png",
        "home_id": "team_20250705_000704581_clublujan_61449763",
        "away_team": "Leones de Rosario",
        "away_team_logo_local": "images/teams/leones_de_rosario_logo.png",
        "away_id": "team_20260308_000640507_leonesderosario_1409f22a",
        "id": "match_20260530_000841936_clublujan_leonesderosario_2130_aa9123",
        "status": "scheduled",
        "predictions": {
          "algorithm_version": "FINAL_BIVARIATE_POISSON_v2.0",
          "simulation_count": 100000,
          "top_3_correct_scores": [
            {
              "score": "1-1",
              "percentage": 9.74
            },
            {
              "score": "2-1",
              "percentage": 9.57
            },
            {
              "score": "1-0",
              "percentage": 9.33
            }
          ],
          "most_likely_halftime_score": {
            "score": "1-0",
            "percentage": 16.71
          },
          "goals_markets": {
            "over_1_5": 76.56,
            "over_2_5": 55.37,
            "under_2_5": 44.63,
            "under_3_5": 64.39
          },
          "teams_markets": {
            "both_teams_score": 55.32
          },
          "market_analysis": {
            "home_win_prob": 0.370440349434281,
            "draw_prob": 0.3300286749505413,
            "away_win_prob": 0.2995309756151777,
            "market_efficiency": 0.9075788561139886,
            "goal_expectancy": 0.09,
            "overround": 0.10183263224281602,
            "odds_strength_ratio": 1.2367346938775508
          },
          "team_values": {
            "home_team_value": 69.9,
            "away_team_value": 67.4
          }
        }
      },
      {
        "time": "21:30",
        "odds": [
          "2.78",
          "2.81",
          "2.52"
        ],
        "home_team": "Puerto Nuevo",
        "home_team_logo_local": "images/teams/puerto_nuevo_logo.png",
        "home_id": "team_20250707_013047606_puertonuevo_f89b7d1d",
        "away_team": "Mercedes",
        "away_team_logo_local": "images/teams/mercedes_logo.png",
        "away_id": "team_20250721_004457921_mercedes_07434c24",
        "id": "match_20260530_000852576_puertonuevo_mercedes_2130_0e8843",
        "status": "scheduled",
        "predictions": {
          "algorithm_version": "FINAL_BIVARIATE_POISSON_v2.0",
          "simulation_count": 100000,
          "top_3_correct_scores": [
            {
              "score": "1-1",
              "percentage": 12.04
            },
            {
              "score": "1-0",
              "percentage": 8.88
            },
            {
              "score": "2-1",
              "percentage": 8.64
            }
          ],
          "most_likely_halftime_score": {
            "score": "1-1",
            "percentage": 17.37
          },
          "goals_markets": {
            "over_1_5": 74.14,
            "over_2_5": 51.92,
            "under_2_5": 48.08,
            "under_3_5": 67.92
          },
          "teams_markets": {
            "both_teams_score": 56.37
          },
          "market_analysis": {
            "home_win_prob": 0.3233631373695122,
            "draw_prob": 0.31991086188158147,
            "away_win_prob": 0.35672600074890626,
            "market_efficiency": 0.8989495218872439,
            "goal_expectancy": 0.08279999999999998,
            "overround": 0.1124095131622207,
            "odds_strength_ratio": 0.9064748201438849
          },
          "team_values": {
            "home_team_value": 54.1,
            "away_team_value": 51.8
          }
        }
      }
    ],
    "total_matches": 7
  },
  {
    "name": "Copa Argentina",
    "country": "ARGENTINA",
    "flag_icon_local": "images/competitions/copa_argentina_flag.png",
    "matches": [
      {
        "time": "21:30",
        "odds": [
          "3.46",
          "2.96",
          "2.12"
        ],
        "home_team": "Gimnasia Jujuy",
        "home_team_logo_local": "images/teams/gimnasia_jujuy_logo.png",
        "home_id": "team_20250705_000422300_gimnasiajujuy_0e8daef2",
        "away_team": "Belgrano",
        "away_team_logo_local": "images/teams/belgrano_logo.png",
        "away_id": "team_20250712_000301940_belgrano_4a9c9549",
        "id": "match_20260530_001032847_gimnasiajujuy_belgrano_2130_03f016",
        "status": "scheduled",
        "predictions": {
          "algorithm_version": "FINAL_BIVARIATE_POISSON_v2.0",
          "simulation_count": 100000,
          "top_3_correct_scores": [
            {
              "score": "0-0",
              "percentage": 12.28
            },
            {
              "score": "1-0",
              "percentage": 12.22
            },
            {
              "score": "0-1",
              "percentage": 11.96
            }
          ],
          "most_likely_halftime_score": {
            "score": "0-1",
            "percentage": 18.43
          },
          "goals_markets": {
            "over_1_5": 64.09,
            "over_2_5": 40.35,
            "under_2_5": 59.65,
            "under_3_5": 77.75
          },
          "teams_markets": {
            "both_teams_score": 47.08
          },
          "market_analysis": {
            "home_win_prob": 0.2630890491363408,
            "draw_prob": 0.3075297668958578,
            "away_win_prob": 0.4293811839678014,
            "market_efficiency": 0.910288110011739,
            "goal_expectancy": 0.0648,
            "overround": 0.0985532920858474,
            "odds_strength_ratio": 0.6127167630057804
          },
          "team_values": {
            "home_team_value": 62.8,
            "away_team_value": 72.4
          }
        }
      }
    ],
    "total_matches": 1
  },
  {
    "name": "NPL ACT",
    "country": "AUSTRALIA",
    "flag_icon_local": "images/competitions/npl_act_flag.png",
    "matches": [
      {
        "time": "08:00",
        "odds": [
          "2.51",
          "3.78",
          "2.22"
        ],
        "home_team": "Canberra Juventus",
        "home_team_logo_local": "images/teams/canberra_juventus_logo.png",
        "home_id": "team_20250704_004653793_canberrajuventus_dbd852a6",
        "away_team": "Tuggeranong Utd",
        "away_team_logo_local": "images/teams/tuggeranong_utd_logo.png",
        "away_id": "team_20250628_033218957_tuggeranongutd_a5db5233",
        "id": "match_20260530_001143521_canberrajuventus_tuggeranongutd_0800_e0bf37",
        "status": "scheduled",
        "predictions": {
          "algorithm_version": "FINAL_BIVARIATE_POISSON_v2.0",
          "simulation_count": 100000,
          "top_3_correct_scores": [
            {
              "score": "1-0",
              "percentage": 16.69
            },
            {
              "score": "2-0",
              "percentage": 12.49
            },
            {
              "score": "0-0",
              "percentage": 9.36
            }
          ],
          "most_likely_halftime_score": {
            "score": "1-0",
            "percentage": 23.41
          },
          "goals_markets": {
            "over_1_5": 67.3,
            "over_2_5": 44.02,
            "under_2_5": 55.98,
            "under_3_5": 74.58
          },
          "teams_markets": {
            "both_teams_score": 42.43
          },
          "market_analysis": {
            "home_win_prob": 0.357826331678862,
            "draw_prob": 0.2376042572788211,
            "away_win_prob": 0.40456941104231686,
            "market_efficiency": 0.8981440925139436,
            "goal_expectancy": -0.03359999999999998,
            "overround": 0.11340708950270706,
            "odds_strength_ratio": 0.8844621513944224
          },
          "team_values": {
            "home_team_value": 66.5,
            "away_team_value": 44.0
          }
        }
      },
      {
        "time": "08:00",
        "odds": [
          "2.93",
          "3.92",
          "1.98"
        ],
        "home_team": "O'Connor Knights",
        "home_team_logo_local": "images/teams/oconnor_knights_logo.png",
        "home_id": "team_20250704_004219132_oconnorknights_3b00c958",
        "away_team": "Queanbeyan City",
        "away_team_logo_local": "images/teams/queanbeyan_city_logo.png",
        "away_id": "team_20250704_004229224_queanbeyancity_e2ee523a",
        "id": "match_20260530_001153704_oconnorknights_queanbeyancity_0800_301b54",
        "status": "scheduled",
        "predictions": {
          "algorithm_version": "FINAL_BIVARIATE_POISSON_v2.0",
          "simulation_count": 100000,
          "top_3_correct_scores": [
            {
              "score": "0-1",
              "percentage": 12.96
            },
            {
              "score": "1-1",
              "percentage": 11.02
            },
            {
              "score": "1-2",
              "percentage": 9.23
            }
          ],
          "most_likely_halftime_score": {
            "score": "0-1",
            "percentage": 15.24
          },
          "goals_markets": {
            "over_1_5": 69.33,
            "over_2_5": 46.55,
            "under_2_5": 53.45,
            "under_3_5": 72.67
          },
          "teams_markets": {
            "both_teams_score": 51.25
          },
          "market_analysis": {
            "home_win_prob": 0.3098616289932371,
            "draw_prob": 0.2316057584056594,
            "away_win_prob": 0.45853261260110345,
            "market_efficiency": 0.9078945729501848,
            "goal_expectancy": -0.050399999999999986,
            "overround": 0.1014494741944767,
            "odds_strength_ratio": 0.6757679180887372
          },
          "team_values": {
            "home_team_value": 38.0,
            "away_team_value": 66.2
          }
        }
      },
      {
        "time": "09:00",
        "odds": [
          "5.73",
          "5.90",
          "1.32"
        ],
        "home_team": "Brindabella",
        "home_team_logo_local": "images/teams/brindabella_logo.png",
        "home_id": "team_20250704_004703202_brindabella_22ea863e",
        "away_team": "Canberra Olympic",
        "away_team_logo_local": "images/teams/canberra_olympic_logo.png",
        "away_id": "team_20250705_000948613_canberraolympic_37892d03",
        "id": "match_20260530_001203855_brindabella_canberraolympic_0900_5be52a",
        "status": "scheduled",
        "predictions": {
          "algorithm_version": "FINAL_BIVARIATE_POISSON_v2.0",
          "simulation_count": 100000,
          "top_3_correct_scores": [
            {
              "score": "1-2",
              "percentage": 10.96
            },
            {
              "score": "1-1",
              "percentage": 7.8
            },
            {
              "score": "0-1",
              "percentage": 7.64
            }
          ],
          "most_likely_halftime_score": {
            "score": "1-1",
            "percentage": 13.34
          },
          "goals_markets": {
            "over_1_5": 77.58,
            "over_2_5": 57.39,
            "under_2_5": 42.6,
            "under_3_5": 62.0
          },
          "teams_markets": {
            "both_teams_score": 57.32
          },
          "market_analysis": {
            "home_win_prob": 0.15842599260353227,
            "draw_prob": 0.15386117586749828,
            "away_win_prob": 0.6877128315289696,
            "market_efficiency": 0.9077809376182399,
            "goal_expectancy": -0.12,
            "overround": 0.10158735280751419,
            "odds_strength_ratio": 0.23036649214659685
          },
          "team_values": {
            "home_team_value": 40.5,
            "away_team_value": 58.5
          }
        }
      }
    ],
    "total_matches": 3
  }
]